{
    "products": [
        {
            "id": "OLJCESPC7Z",
            "name": "Rolex Submariner",
            "description": "A timeless dive watch, synonymous with prestige, precision, and enduring style.",
            "picture": "static/img/products/watch.JPG",
            "cost": 9100.00,
            "categories": ["jewelry"]
        },
        {
            "id": "66VCHSJNUP",
            "name": "Range Rover SUV",
            "description": "The epitome of luxury SUVs, combining unparalleled comfort, capability, and sophistication for discerning adventurers.",
            "picture": "static/img/products/range-rover.JPG",
            "cost": 107400.00,
            "categories": ["automobiles"]
        },
        {
            "id": "1YMWWN1N4O",
            "name": "U. Penn Quarter Zip",
            "description": "Elevate casual style with this versatile, comfortable, and effortlessly cool wardrobe essential.",
            "picture": "static/img/products/quarter-zip.JPG",
            "cost": 149,
            "categories": ["clothing"]
        },
        {
            "id": "L9ECAV7KIM",
            "name": "Visualizing Google Cloud",
            "description": "A comprehensive guide to harnessing the power of Google Cloud through illustrative insights.",
            "picture": "static/img/products/book.JPG",
            "cost": 27.99,
            "categories": ["books"]
        },
        {
            "id": "2ZYFJ3GM2N",
            "name": "Bowers & Wilkens Earbuds",
            "description": "Premium sound and style, delivering an exceptional wireless audio experience.",
            "picture": "static/img/products/earbuds.JPG",
            "cost": 399.00,
            "categories": ["electronics"]
        },
        {
            "id": "0PUK6V6EV0",
            "name": "Breville Espresso Machine",
            "description": "Revolutionize your home brewing with automated precision and cafe-quality espresso.",
            "picture": "static/img/products/coffee-machine.JPG",
            "cost": 2199.95,
            "categories": ["appliances"]
        },
        {
            "id": "LS4PSXUNUM",
            "name": "Apple Watch",
            "description": "Your all-in-one wrist companion, seamlessly blending technology, fitness, and style for an active lifestyle.",
            "picture": "static/img/products/apple-watch.JPG",
            "cost": 799.00,
            "categories": ["electronics"]
        },
        {
            "id": "9SIQT8TOJO",
            "name": "Trek Domane Road Bike",
            "description": "Climb the hills of San Francisco effortlessly with this comfortable road racing machine.",
            "picture": "static/img/products/bike.JPG",
            "cost": 3700.00,
            "categories": ["cycling"]
        },
        {
            "id": "6E92ZMYYFZ",
            "name": "Yeti 10oz Rambler",
            "description": "The ultimate insulated tumbler, keeping your drinks hot or cold in rugged style.",
            "picture": "static/img/products/coffee-mug.JPG",
            "cost": 30.00,
            "categories": ["housewares"]
        }
    ]
}
